structurizr/__init__.py
structurizr-0.1.0.dist-info/DESCRIPTION.rst
structurizr-0.1.0.dist-info/METADATA
structurizr-0.1.0.dist-info/RECORD
structurizr-0.1.0.dist-info/WHEEL
structurizr-0.1.0.dist-info/metadata.json
structurizr-0.1.0.dist-info/top_level.txt
